AUTHORS.rst
CHANGELOG.rst
LICENSE
MANIFEST.in
Notes.txt
PythonImpl.py
README.rst
_cpeg.c
_ppeg.c
cpeg.c
lpeg.c
pegmatcher.py
setup.py
PPeg.egg-info/PKG-INFO
PPeg.egg-info/SOURCES.txt
PPeg.egg-info/dependency_links.txt
PPeg.egg-info/top_level.txt