Metadata-Version: 1.1
Name: PPeg
Version: 0.9.3
Summary: A Python port of Lua's LPeg pattern matching library
Home-page: https://github.com/moreati/ppeg
Author: Alex Willmer
Author-email: alex@moreati.org.uk
License: MIT
Keywords: parsing peg grammar regex
Platform: UNKNOWN
Classifier: Development Status :: 3 - Alpha
Classifier: Intended Audience :: Developers
Classifier: License :: OSI Approved :: MIT License
Classifier: Programming Language :: Python :: 2 :: Only
Classifier: Topic :: Text Processing :: General
